fastnotifier/__init__.py
fastnotifier/dingding.py
fastnotifier/feishu.py
fastnotifier/wechat.py
fastnotifier-0.0.9.dist-info/LICENSE
fastnotifier-0.0.9.dist-info/METADATA
fastnotifier-0.0.9.dist-info/WHEEL
fastnotifier-0.0.9.dist-info/top_level.txt
fastnotifier-0.0.9.dist-info/RECORD
