Metadata-Version: 2.1
Name: fastnotifier
Version: 0.0.9
Summary: make it easy to use notifier
Home-page: https://gitee.com/ZeroSeeker/fastnotifier
Author: ZeroSeeker
Author-email: zeroseeker@foxmail.com
Classifier: Programming Language :: Python :: 3
Classifier: License :: OSI Approved :: MIT License
Classifier: Operating System :: OS Independent
License-File: LICENSE
Requires-Dist: requests (>=2.31.0)
Requires-Dist: envx (>=1.0.1)
Requires-Dist: DingtalkChatbot (==1.5.3)
